Metadata-Version: 2.1
Name: slientruss3d
Version: 2.0.2
Summary: 3D and 2D Truss structural analysis
Home-page: https://github.com/leo27945875/Python_Stable_3D_Truss_Analysis
Download-URL: https://github.com/leo27945875/Python_Stable_3D_Truss_Analysis/archive/refs/tags/v2.0.2.tar.gz
Author: Shih-Chi Cheng
Author-email: ezioatiar@gmail.com
License: MIT
Keywords: python,truss,civil engineering,structural analysis
Platform: UNKNOWN
Classifier: Development Status :: 5 - Production/Stable
Classifier: Intended Audience :: Education
Classifier: Intended Audience :: Developers
Classifier: Intended Audience :: Manufacturing
Classifier: Intended Audience :: Science/Research
Classifier: License :: OSI Approved :: MIT License
Classifier: Programming Language :: Python :: 3.9
License-File: LICENSE.txt
